README.md
setup.py
tpyan/__init__.py
tpyan.egg-info/PKG-INFO
tpyan.egg-info/SOURCES.txt
tpyan.egg-info/dependency_links.txt
tpyan.egg-info/requires.txt
tpyan.egg-info/top_level.txt
tpyan/authkey/__init__.py
tpyan/autoscrollbar/__init__.py
tpyan/autoscrollbar/autoscrbar.py
tpyan/caculate/__init__.py
tpyan/caculate/area.py
tpyan/caculate/cacul_cavas.py
tpyan/caculate/coord_point.py
tpyan/caculate/ratio.py
tpyan/cavas_dim/__init__.py
tpyan/cavas_dim/cavas_dim.py
tpyan/cavas_drawing/__init__.py
tpyan/cavas_drawing/buttondr.py
tpyan/cavas_drawing/draw.py
tpyan/cavas_write/__init__.py
tpyan/cavas_write/writetext.py
tpyan/cavaszm/__init__.py
tpyan/cavaszm/cavaszm.py
tpyan/check/Hstr_StrRetrFile_1.py
tpyan/check/__init__.py
tpyan/check/list.py
tpyan/checklb/__init__.py
tpyan/checklb/checkb.py
tpyan/crypt/__init__.py
tpyan/csv/__init__.py
tpyan/csv/rcsv.py
tpyan/csv/tocsv.py
tpyan/csv/todict.py
tpyan/csv/tolist.py
tpyan/ctn/__init__.py
tpyan/data/__init__.py
tpyan/data/filename.py
tpyan/data/hdata.py
tpyan/dict/__init__.py
tpyan/dict/createdict.py
tpyan/dict/csv.py
tpyan/error/__init__.py
tpyan/error/cerror.py
tpyan/excel/Fill_formula.py
tpyan/excel/__init__.py
tpyan/excel/convertexelltocsv.py
tpyan/excel/copy_move_paste.py
tpyan/excel/copyexcel.py
tpyan/excel/copypasteexell.py
tpyan/excel/crelistadict.py
tpyan/excel/del_row.py
tpyan/excel/delete.py
tpyan/excel/fexcell.py
tpyan/excel/fformulaexcel.py
tpyan/excel/fomulas.py
tpyan/excel/hdata.py
tpyan/excel/hexcel.py
tpyan/excel/hrow.py
tpyan/excel/lexcel.py
tpyan/excel/list.py
tpyan/excel/path.py
tpyan/excel/toexcel.py
tpyan/excel/write.py
tpyan/excel/exception/__init__.py
tpyan/excel/openpyxl/__init__.py
tpyan/excel/rows/__init__.py
tpyan/folder/__init__.py
tpyan/folder/list.py
tpyan/gdrive/__init__.py
tpyan/gdrive/sheet.py
tpyan/ggdrive/__init__.py
tpyan/ggdrive/auth.py
tpyan/hlstr/__init__.py
tpyan/hlstr/hlstr.py
tpyan/iter/__init__.py
tpyan/list/__init__.py
tpyan/list/flist.py
tpyan/list/str.py
tpyan/list/tocsv.py
tpyan/list/twolist.py
tpyan/login/__init__.py
tpyan/login/atadlogin.py
tpyan/mc_id/__init__.py
tpyan/nsew/__init__.py
tpyan/nsew/nsew.py
