Metadata-Version: 2.1
Name: tpyan
Version: 0.0.0
Summary: python for excel
Home-page: UNKNOWN
Author: Nguyen Van Nhuan
Author-email: <nhuannv.vs@gmail.com>
License: UNKNOWN
Keywords: python,python excel,pyan,pyexcel
Platform: UNKNOWN
Classifier: Development Status :: 1 - Planning
Classifier: Intended Audience :: Developers
Classifier: Programming Language :: Python :: 3
Classifier: Operating System :: Unix
Classifier: Operating System :: MacOS :: MacOS X
Classifier: Operating System :: Microsoft :: Windows
